nativesvttk/__init__.py
nativesvttk/messagebox.py
nativesvttk/py.typed
nativesvttk/sv.tcl
nativesvttk/theme/dark.tcl
nativesvttk/theme/light.tcl
nativesvttk/theme/sprites_dark.tcl
nativesvttk/theme/sprites_light.tcl
nativesvttk/theme/spritesheet_dark.png
nativesvttk/theme/spritesheet_light.png
nativesvttk-14.dist-info/WHEEL
nativesvttk-14.dist-info/METADATA
nativesvttk-14.dist-info/RECORD
