Metadata-Version: 2.1
Name: nativesvttk
Version: 14
Summary: Even more windows 11-like! With custom titlebars, Making themed apps is now so easy! 
Author-email: Johnny <johnny@johnnytech.net>
Requires-Python: >=3.8
Classifier: License :: OSI Approved :: MIT License
